pkgexampledatabases/__init__.py
pkgexampledatabases/appconfig.yaml
pkgexampledatabases/my_database_module.py
pkgexampledatabases/myappconfigmanager.py
pkgexampledatabases/mycsvhelper.py
pkgexampledatabases/mydatabasemanager.py
pkgexampledatabases/mypathmanager.py
pkgexampledatabases/mysqlitemanager.py
pkgexampledatabases/data/__init__.py
pkgexampledatabases/data/config/__init__.py
pkgexampledatabases/data/config/packagedb.json
pkgexampledatabases/data/config/userdb.json
pkgexampledatabases/data/sampledata/__init__.py
pkgexampledatabases/data/sampledata/shoppinglist.csv
pkgexampledatabases/data/sampledata/store.csv
pkgexampledatabases-0.0.5.dist-info/LICENCE
pkgexampledatabases-0.0.5.dist-info/METADATA
pkgexampledatabases-0.0.5.dist-info/WHEEL
pkgexampledatabases-0.0.5.dist-info/entry_points.txt
pkgexampledatabases-0.0.5.dist-info/top_level.txt
pkgexampledatabases-0.0.5.dist-info/RECORD
