Metadata-Version: 2.1
Name: pkgexampledatabases
Version: 0.0.5
Summary: A simple database package example
Author-email: Good Boy <pythonic@rexbytes.com>
Project-URL: Homepage, https://github.com/RexBytes/pkgexampledatabases
Project-URL: Bug Tracker, https://github.com/RexBytes/pkgexampledatabases/issues
Project-URL: Download URL, https://github.com/RexBytes/pkgexampledatabases/archive/refs/tags/v0.0.5.tar.gz
Classifier: Programming Language :: Python :: 3
Classifier: License :: OSI Approved :: MIT License
Classifier: Operating System :: OS Independent
Requires-Python: >=3.7
License-File: LICENCE
